vnpy_uf/__init__.py
vnpy_uf/api/__init__.py
vnpy_uf/api/license.dat
vnpy_uf/api/py_t2sdk.pyd
vnpy_uf/api/t2sdk.dll
vnpy_uf/gateway/__init__.py
vnpy_uf/gateway/uf_gateway.py
vnpy_uf-1.0.1.dist-info/LICENSE
vnpy_uf-1.0.1.dist-info/METADATA
vnpy_uf-1.0.1.dist-info/WHEEL
vnpy_uf-1.0.1.dist-info/top_level.txt
vnpy_uf-1.0.1.dist-info/RECORD
