Metadata-Version: 2.1
Name: vnpy-uf
Version: 1.0.1
Summary: Hundsun UF2.0 gateway for vn.py quant trading framework.
Home-page: https://www.vnpy.com
Author: Xiaoyou Chen
Author-email: xiaoyou.chen@mail.vnpy.com
License: MIT
Keywords: quant,quantitative,investment,trading,algotrading
Platform: UNKNOWN
Classifier: Development Status :: 5 - Production/Stable
Classifier: Operating System :: Microsoft :: Windows
Classifier: Operating System :: POSIX :: Linux
Classifier: Programming Language :: Python :: 3
Classifier: Programming Language :: Python :: 3.7
Classifier: Topic :: Office/Business :: Financial :: Investment
Classifier: Programming Language :: Python :: Implementation :: CPython
Classifier: License :: OSI Approved :: MIT License
Classifier: Natural Language :: Chinese (Simplified)
Requires-Python: ==3.7
License-File: LICENSE
Requires-Dist: importlib-metadata
Requires-Dist: tushare
